gevent_fsm/__init__.py
gevent_fsm/conf.py
gevent_fsm/fsm.py
gevent_fsm/messages.py
gevent_fsm/templates/fsm.pyt
gevent_fsm/tools/__init__.py
gevent_fsm/tools/extract_fsm.py
gevent_fsm/tools/fsm_diff.py
gevent_fsm/tools/fsm_generate_diffs.py
gevent_fsm/tools/get_fsm.py
gevent_fsm/tools/transform_fsm.py
gevent_fsm-0.2.2.dist-info/AUTHORS.rst
gevent_fsm-0.2.2.dist-info/LICENSE
gevent_fsm-0.2.2.dist-info/METADATA
gevent_fsm-0.2.2.dist-info/WHEEL
gevent_fsm-0.2.2.dist-info/entry_points.txt
gevent_fsm-0.2.2.dist-info/top_level.txt
gevent_fsm-0.2.2.dist-info/RECORD
