Metadata-Version: 2.1
Name: gevent-fsm
Version: 0.2.2
Summary: Finite State Machines with Gevent
Home-page: https://github.com/benthomasson/gevent-fsm
Author: Ben Thomasson
Author-email: ben.thomasson@gmail.com
License: Apache Software License 2.0
Keywords: gevent_fsm
Platform: UNKNOWN
Classifier: Development Status :: 2 - Pre-Alpha
Classifier: Intended Audience :: Developers
Classifier: License :: OSI Approved :: Apache Software License
Classifier: Natural Language :: English
Classifier: Programming Language :: Python :: 2
Classifier: Programming Language :: Python :: 2.7
Classifier: Programming Language :: Python :: 3
Classifier: Programming Language :: Python :: 3.4
Classifier: Programming Language :: Python :: 3.5
Classifier: Programming Language :: Python :: 3.6
Classifier: Programming Language :: Python :: 3.7
Requires-Dist: gevent
Requires-Dist: docopt
Requires-Dist: requests
